prosit/__init__.py
prosit/prosit.py
prosit-0.1.5.dist-info/AUTHORS.rst
prosit-0.1.5.dist-info/LICENSE
prosit-0.1.5.dist-info/METADATA
prosit-0.1.5.dist-info/WHEEL
prosit-0.1.5.dist-info/top_level.txt
prosit-0.1.5.dist-info/RECORD
