Metadata-Version: 2.1
Name: prosit
Version: 0.1.5
Summary: A topic models algorithm
Home-page: https://github.com/fornaciari/prosit
Author: Tommaso Fornaciari
Author-email: tommaso.fornaciari@poliziadistato.it
License: MIT license
Classifier: Programming Language :: Python :: 3.7
Classifier: License :: OSI Approved :: GNU General Public License v3 (GPLv3)
Requires-Python: >=3.6
License-File: LICENSE
License-File: AUTHORS.rst
Requires-Dist: pip (==21.0.1)
Requires-Dist: wheel (==0.37.1)
Requires-Dist: twine (==3.3.0)
Requires-Dist: scipy
Requires-Dist: pandas
Requires-Dist: numpy
Requires-Dist: sklearn
Requires-Dist: torch
Requires-Dist: gensim
Requires-Dist: contextualized-topic-models
Requires-Dist: matplotlib
Requires-Dist: seaborn
Requires-Dist: imageio
